setup.py
djradicale/__init__.py
djradicale/admin.py
djradicale/config.py
djradicale/models.py
djradicale/urls.py
djradicale/views.py
djradicale.egg-info/PKG-INFO
djradicale.egg-info/SOURCES.txt
djradicale.egg-info/dependency_links.txt
djradicale.egg-info/requires.txt
djradicale.egg-info/top_level.txt
djradicale/auth/__init__.py
djradicale/auth/django.py
djradicale/migrations/0001_initial.py
djradicale/migrations/__init__.py
djradicale/rights/__init__.py
djradicale/rights/django.py
djradicale/storage/__init__.py
djradicale/storage/django.py
djradicale/tests/__init__.py
djradicale/tests/test_caldav.py
djradicale/tests/test_carddav.py
djradicale/tests/test_serialize.py