Metadata-Version: 1.1
Name: djradicale
Version: 0.0.14
Summary: Radicale is a free and open-source CalDAV and CardDAV server.DjRadicale is an Django Application for integration Radicale with a Django.
Home-page: https://github.com/kyokenn/djradicale
Author: Kyoken
Author-email: kyoken@kyoken.ninja
License: GPLv3
Keywords: django radicale carddav caldav
Platform: UNKNOWN
Classifier: Development Status :: 3 - Alpha
Classifier: Programming Language :: Python :: 3
Classifier: License :: OSI Approved :: GNU General Public License v3 or later (GPLv3+)
Classifier: Framework :: Django
